galaxynet/__init__.py
galaxynet/eqx_scorenet32.eqx
galaxynet/eqx_scorenet64.eqx
galaxynet/models_eqx.py
galaxynet/scorenet.py
galaxynet-0.0.13.dist-info/METADATA
galaxynet-0.0.13.dist-info/WHEEL
galaxynet-0.0.13.dist-info/top_level.txt
galaxynet-0.0.13.dist-info/RECORD
