Metadata-Version: 2.1
Name: galaxynet
Version: 0.0.13
Summary: Diffusion model for galaxy generation
Author: Matt Sampson
Author-email: <matt.sampson@princeton.edu
Keywords: python,diffusion
Classifier: Development Status :: 3 - Alpha
Classifier: Intended Audience :: Education
Classifier: Programming Language :: Python :: 3
Classifier: Operating System :: MacOS :: MacOS X
Classifier: Operating System :: Microsoft :: Windows
